[{"category":"anti-social-behaviour","location_type":"Force","location":{"latitude":"54.329311","street":{"id":2262378,"name":"On or near Library Road"},"longitude":"-2.747962"},"context":"","outcome_status":null,"persistent_id":"","id":131007153,"location_subtype":"","month":"2025-08"},{"category":"anti-social-behaviour","location_type":"Force","location":{"latitude":"54.323686","street":{"id":2262436,"name":"On or near Sports/recreation Area"},"longitude":"-2.745200"},"context":"","outcome_status":null,"persistent_id":"","id":131007270,"location_subtype":"","month":"2025-08"},{"category":"anti-social-behaviour","location_type":"Force","location":{"latitude":"54.331637","street":{"id":2262878,"name":"On or near Thirlmere Road"},"longitude":"-2.724675"},"context":"","outcome_status":null,"persistent_id":"","id":131007287,"location_subtype":"","month":"2025-08"},{"category":"anti-social-behaviour","location_type":"Force","location":{"latitude":"54.317251","street":{"id":2262894,"name":"On or near Littledale"},"longitude":"-2.725652"},"context":"","outcome_status":null,"persistent_id":"","id":131007235,"location_subtype":"","month":"2025-08"},{"category":"anti-social-behaviour","location_type":"Force","location":{"latitude":"54.334401","street":{"id":2262767,"name":"On or near Garburn Road"},"longitude":"-2.729861"},"context":"","outcome_status":null,"persistent_id":"","id":131007095,"location_subtype":"","month":"2025-08"},{"category":"anti-social-behaviour","location_type":"Force","location":{"latitude":"54.329739","street":{"id":2262434,"name":"On or near Bus/coach Station"},"longitude":"-2.745509"},"context":"","outcome_status":null,"persistent_id":"","id":131007200,"location_subtype":"","month":"2025-08"},{"category":"anti-social-behaviour","location_type":"Force","location":{"latitude":"54.328431","street":{"id":2262423,"name":"On or near Branthwaite Brow"},"longitude":"-2.746408"},"context":"","outcome_status":null,"persistent_id":"","id":131007216,"location_subtype":"","month":"2025-08"},{"category":"anti-social-behaviour","location_type":"Force","location":{"latitude":"54.326638","street":{"id":2262442,"name":"On or near Gulfs Road"},"longitude":"-2.745684"},"context":"","outcome_status":null,"persistent_id":"","id":131007225,"location_subtype":"","month":"2025-08"},{"category":"anti-social-behaviour","location_type":"Force","location":{"latitude":"54.327546","street":{"id":2262366,"name":"On or near Old Shambles"},"longitude":"-2.748576"},"context":"","outcome_status":null,"persistent_id":"","id":131007263,"location_subtype":"","month":"2025-08"},{"category":"anti-social-behaviour","location_type":"Force","location":{"latitude":"54.329311","street":{"id":2262378,"name":"On or near Library Road"},"longitude":"-2.747962"},"context":"","outcome_status":null,"persistent_id":"","id":131007162,"location_subtype":"","month":"2025-08"},{"category":"anti-social-behaviour","location_type":"Force","location":{"latitude":"54.323686","street":{"id":2262436,"name":"On or near Sports/recreation Area"},"longitude":"-2.745200"},"context":"","outcome_status":null,"persistent_id":"","id":131007082,"location_subtype":"","month":"2025-08"},{"category":"anti-social-behaviour","location_type":"Force","location":{"latitude":"54.330853","street":{"id":2262502,"name":"On or near Parking Area"},"longitude":"-2.741316"},"context":"","outcome_status":null,"persistent_id":"","id":131007286,"location_subtype":"","month":"2025-08"},{"category":"burglary","location_type":"Force","location":{"latitude":"54.335672","street":{"id":2262568,"name":"On or near Mint Street"},"longitude":"-2.738142"},"context":"","outcome_status":{"category":"Status update unavailable","date":"2025-12"},"persistent_id":"7b4a6171dd7c8e467ba351a38586e19b60d21e87ffe54610b0c29311ea7c64e0","id":131005934,"location_subtype":"","month":"2025-08"},{"category":"burglary","location_type":"Force","location":{"latitude":"54.325115","street":{"id":2262422,"name":"On or near Kent Place"},"longitude":"-2.746287"},"context":"","outcome_status":{"category":"Unable to prosecute suspect","date":"2025-09"},"persistent_id":"50d7747686a3e6370449e1ccec7720da23c15e2bccdbea01d491bbf05ab0304c","id":131005094,"location_subtype":"","month":"2025-08"},{"category":"burglary","location_type":"Force","location":{"latitude":"54.338627","street":{"id":2262587,"name":"On or near Finley Drive"},"longitude":"-2.739764"},"context":"","outcome_status":{"category":"Investigation complete; no suspect identified","date":"2025-09"},"persistent_id":"9efaa81481cf8f230d31890a7c8f8630ac211425b01c361bde97df1e6a26ef07","id":131006017,"location_subtype":"","month":"2025-08"},{"category":"burglary","location_type":"Force","location":{"latitude":"54.338627","street":{"id":2262587,"name":"On or near Finley Drive"},"longitude":"-2.739764"},"context":"","outcome_status":{"category":"Investigation complete; no suspect identified","date":"2025-11"},"persistent_id":"a2f830c1748906f8bc8aae9ec54f6ca124ce72e55f0eb26d7777cd8d57b26d5d","id":131006315,"location_subtype":"","month":"2025-08"},{"category":"burglary","location_type":"Force","location":{"latitude":"54.332871","street":{"id":2262858,"name":"On or near Rydal Road"},"longitude":"-2.727188"},"context":"","outcome_status":{"category":"Investigation complete; no suspect identified","date":"2025-12"},"persistent_id":"556d9d8aebc1f9b5d11f9639f116df27baf2c62141dcd9333f646b4c6a8a0d48","id":131005620,"location_subtype":"","month":"2025-08"},{"category":"burglary","location_type":"Force","location":{"latitude":"54.334883","street":{"id":2262409,"name":"On or near Mintsfeet Road South"},"longitude":"-2.743541"},"context":"","outcome_status":{"category":"Investigation complete; no suspect identified","date":"2025-09"},"persistent_id":"e0e222072b017f325df41fe7c8659a7a8e57d077ae9ecb4b65157fdcea62a1f6","id":131004839,"location_subtype":"","month":"2025-08"},{"category":"burglary","location_type":"Force","location":{"latitude":"54.326918","street":{"id":2262729,"name":"On or near Castle Walk"},"longitude":"-2.732281"},"context":"","outcome_status":{"category":"Status update unavailable","date":"2025-12"},"persistent_id":"bcd9d383dbfb832e7adde816d84984137935051212f09511a85944cffb31ee2c","id":131006288,"location_subtype":"","month":"2025-08"},{"category":"burglary","location_type":"Force","location":{"latitude":"54.334883","street":{"id":2262409,"name":"On or near Mintsfeet Road South"},"longitude":"-2.743541"},"context":"","outcome_status":{"category":"Investigation complete; no suspect identified","date":"2025-09"},"persistent_id":"c862c1c6f52a7eb24bc6fb606d1ad9ab6c428da4b5f31756afccbbdbdf3747e4","id":131005118,"location_subtype":"","month":"2025-08"},{"category":"burglary","location_type":"Force","location":{"latitude":"54.330741","street":{"id":2262576,"name":"On or near Ann Street"},"longitude":"-2.739022"},"context":"","outcome_status":{"category":"Investigation complete; no suspect identified","date":"2025-09"},"persistent_id":"1fd5e1bebc14e1b3a8d639c9258ef3d1b35be2fa4326cfb7864b61efb51d62d4","id":131006187,"location_subtype":"","month":"2025-08"},{"category":"criminal-damage-arson","location_type":"Force","location":{"latitude":"54.329093","street":{"id":2262705,"name":"On or near Castle Road"},"longitude":"-2.733765"},"context":"","outcome_status":{"category":"Investigation complete; no suspect identified","date":"2025-08"},"persistent_id":"ed4f0abe40deaa8f63594fab81a8765fc548c914f7345511ee824b05ac0e2dad","id":131006419,"location_subtype":"","month":"2025-08"},{"category":"criminal-damage-arson","location_type":"Force","location":{"latitude":"54.332836","street":{"id":2262796,"name":"On or near Langdale Crescent"},"longitude":"-2.728495"},"context":"","outcome_status":{"category":"Investigation complete; no suspect identified","date":"2025-11"},"persistent_id":"36cc0ac1f1fc06e71908711203c128601d4bd83cf3f42882a3ae6db96c2a90b7","id":131004880,"location_subtype":"","month":"2025-08"},{"category":"criminal-damage-arson","location_type":"Force","location":{"latitude":"54.322806","street":{"id":2262392,"name":"On or near Chapel Lane"},"longitude":"-2.747598"},"context":"","outcome_status":{"category":"Status update unavailable","date":"2025-12"},"persistent_id":"90c3b01e0ce18fc40b39a9a24f23622bee54d2983d271ebe333df3d70bad4f02","id":131004160,"location_subtype":"","month":"2025-08"},{"category":"criminal-damage-arson","location_type":"Force","location":{"latitude":"54.321931","street":{"id":2262447,"name":"On or near Kirkland"},"longitude":"-2.745214"},"context":"","outcome_status":{"category":"Status update unavailable","date":"2025-12"},"persistent_id":"7d2bacddc75758c09ab44f46031efe394a37f10513d18bee3a4827892aa84c1b","id":131004118,"location_subtype":"","month":"2025-08"},{"category":"criminal-damage-arson","location_type":"Force","location":{"latitude":"54.332871","street":{"id":2262858,"name":"On or near Rydal Road"},"longitude":"-2.727188"},"context":"","outcome_status":{"category":"Local resolution","date":"2025-09"},"persistent_id":"3dc3ee7de065a5d6f723bfc02269ea227b1096c0e9d78a728f7af3ed109ab912","id":131005787,"location_subtype":"","month":"2025-08"},{"category":"criminal-damage-arson","location_type":"Force","location":{"latitude":"54.330722","street":{"id":2262532,"name":"On or near Wildman Street"},"longitude":"-2.740652"},"context":"","outcome_status":{"category":"Investigation complete; no suspect identified","date":"2025-08"},"persistent_id":"71f13a259407e88c6c2534cb4ce30bd675cfadea92463f27d8e323392bf02481","id":131006566,"location_subtype":"","month":"2025-08"},{"category":"criminal-damage-arson","location_type":"Force","location":{"latitude":"54.324274","street":{"id":2262697,"name":"On or near Sports/recreation Area"},"longitude":"-2.733573"},"context":"","outcome_status":{"category":"Unable to prosecute suspect","date":"2025-08"},"persistent_id":"01dfb90e9487bd4b07c4b7f759b099ced719663a74f30e7294b1f3e3388eb46d","id":131004717,"location_subtype":"","month":"2025-08"},{"category":"criminal-damage-arson","location_type":"Force","location":{"latitude":"54.326235","street":{"id":2262360,"name":"On or near Collin Croft"},"longitude":"-2.748306"},"context":"","outcome_status":{"category":"Unable to prosecute suspect","date":"2025-10"},"persistent_id":"a86392ec20934434a5a166bc90b66ec517e23110c646c75aa65ebde4a01de7ad","id":131006453,"location_subtype":"","month":"2025-08"},{"category":"criminal-damage-arson","location_type":"Force","location":{"latitude":"54.330722","street":{"id":2262532,"name":"On or near Wildman Street"},"longitude":"-2.740652"},"context":"","outcome_status":{"category":"Unable to prosecute suspect","date":"2025-10"},"persistent_id":"9e784030a2734562cd4e9ae1a0dcfa9e3b3fece446d9d4e41f8dcc41ecf33723","id":131006225,"location_subtype":"","month":"2025-08"},{"category":"criminal-damage-arson","location_type":"Force","location":{"latitude":"54.332140","street":{"id":2262287,"name":"On or near Town View"},"longitude":"-2.751135"},"context":"","outcome_status":{"category":"Awaiting court outcome","date":"2025-10"},"persistent_id":"356272f69b85c0b7e92a6d5b26bf0ebcda64bd61d2024a2fb4eeb92bdff61725","id":131004815,"location_subtype":"","month":"2025-08"},{"category":"criminal-damage-arson","location_type":"Force","location":{"latitude":"54.321490","street":{"id":2262373,"name":"On or near Brockbeck"},"longitude":"-2.748220"},"context":"","outcome_status":{"category":"Status update unavailable","date":"2025-12"},"persistent_id":"c20a9b5d8d985be6b65ad23a63de91e314bd058c68abb9037dcec2852ee99d6d","id":131006253,"location_subtype":"","month":"2025-08"},{"category":"criminal-damage-arson","location_type":"Force","location":{"latitude":"54.338627","street":{"id":2262587,"name":"On or near Finley Drive"},"longitude":"-2.739764"},"context":"","outcome_status":{"category":"Investigation complete; no suspect identified","date":"2025-10"},"persistent_id":"4cc8f6b445f5132a256199df8cc37b0adf077d6cd3d548c0feecc466a00037b8","id":131006728,"location_subtype":"","month":"2025-08"},{"category":"drugs","location_type":"Force","location":{"latitude":"54.330722","street":{"id":2262532,"name":"On or near Wildman Street"},"longitude":"-2.740652"},"context":"","outcome_status":{"category":"Status update unavailable","date":"2025-12"},"persistent_id":"0cbcf8f53e6e87ffca5c7a3cf6ba7326b9299fa146952013596bc59a3aa7a701","id":131006223,"location_subtype":"","month":"2025-08"},{"category":"drugs","location_type":"Force","location":{"latitude":"54.332406","street":{"id":2262401,"name":"On or near Police Station"},"longitude":"-2.747321"},"context":"","outcome_status":{"category":"Awaiting court outcome","date":"2025-08"},"persistent_id":"938e06b40742fe41f929d5b8d8d295267fc7d572db14370e3463987bdee88f67","id":131006418,"location_subtype":"","month":"2025-08"},{"category":"drugs","location_type":"Force","location":{"latitude":"54.320401","street":{"id":2262224,"name":"On or near Echo Barn Hill"},"longitude":"-2.752766"},"context":"","outcome_status":{"category":"Local resolution","date":"2025-11"},"persistent_id":"734997c7bdc962d80ffd1021bf510ba1d6ff60ebbccda85e37b38637a3c8df93","id":131004736,"location_subtype":"","month":"2025-08"},{"category":"other-theft","location_type":"Force","location":{"latitude":"54.337366","street":{"id":2262553,"name":"On or near Rosemede Avenue"},"longitude":"-2.740341"},"context":"","outcome_status":{"category":"Investigation complete; no suspect identified","date":"2025-08"},"persistent_id":"c49af9186821801f30def74a8ddb6db90e9b3f77a45924b708eb70027a1ad55a","id":131004547,"location_subtype":"","month":"2025-08"},{"category":"other-theft","location_type":"Force","location":{"latitude":"54.319288","street":{"id":2262375,"name":"On or near Glebe Road"},"longitude":"-2.746888"},"context":"","outcome_status":{"category":"Unable to prosecute suspect","date":"2025-09"},"persistent_id":"b26bc2e2f00817572608ac6486a7ec1325bf87c01507d1ff62f71545c90476f8","id":131004399,"location_subtype":"","month":"2025-08"},{"category":"other-theft","location_type":"Force","location":{"latitude":"54.338502","street":{"id":2262583,"name":"On or near Petrol Station"},"longitude":"-2.739623"},"context":"","outcome_status":{"category":"Further investigation is not in the public interest","date":"2025-11"},"persistent_id":"9ea95eab6ff6360eeeeb2a8d92e0b16d96601b5f7ba422a110a198bbf61675fb","id":131006491,"location_subtype":"","month":"2025-08"},{"category":"other-theft","location_type":"Force","location":{"latitude":"54.333898","street":{"id":2262728,"name":"On or near Broad Ing Crescent"},"longitude":"-2.732743"},"context":"","outcome_status":{"category":"Status update unavailable","date":"2025-12"},"persistent_id":"d5398b01760e8205cee87e5d05dd0dff345ae2177a7613e00168fb6354451521","id":131003779,"location_subtype":"","month":"2025-08"},{"category":"other-theft","location_type":"Force","location":{"latitude":"54.319230","street":{"id":2262461,"name":"On or near South Road"},"longitude":"-2.744612"},"context":"","outcome_status":{"category":"Unable to prosecute suspect","date":"2025-08"},"persistent_id":"5fb86f4fd718aa81cda38f75c1ba6b69cdf96ca2dc5a0def634cc7d4315a795f","id":131004384,"location_subtype":"","month":"2025-08"},{"category":"other-theft","location_type":"Force","location":{"latitude":"54.332140","street":{"id":2262287,"name":"On or near Town View"},"longitude":"-2.751135"},"context":"","outcome_status":{"category":"Investigation complete; no suspect identified","date":"2025-10"},"persistent_id":"7050e27e5d1b3bf3a605c0fd9f4b5294ce88820b7225838c3d2229ddfccce37e","id":131004766,"location_subtype":"","month":"2025-08"},{"category":"other-theft","location_type":"Force","location":{"latitude":"54.330250","street":{"id":2262358,"name":"On or near Maude Street"},"longitude":"-2.748702"},"context":"","outcome_status":{"category":"Investigation complete; no suspect identified","date":"2025-08"},"persistent_id":"4e00f7556c7e114d0ddd6ce96979689b414aebdc4f46cfde5b9af3d25437522d","id":131004935,"location_subtype":"","month":"2025-08"},{"category":"other-theft","location_type":"Force","location":{"latitude":"54.327546","street":{"id":2262366,"name":"On or near Old Shambles"},"longitude":"-2.748576"},"context":"","outcome_status":{"category":"Unable to prosecute suspect","date":"2025-08"},"persistent_id":"8b99b6af95a95cbbb7f3d8c202e04892877548c05171d96cc5c018a37cef4c3b","id":131004140,"location_subtype":"","month":"2025-08"},{"category":"other-theft","location_type":"Force","location":{"latitude":"54.321731","street":{"id":2262044,"name":"On or near Briarwood"},"longitude":"-2.759985"},"context":"","outcome_status":{"category":"Investigation complete; no suspect identified","date":"2025-08"},"persistent_id":"691d380020f8de66ff61669f73603797c081abc5a35e2a7e911846d581de64dc","id":131005717,"location_subtype":"","month":"2025-08"},{"category":"other-theft","location_type":"Force","location":{"latitude":"54.327823","street":{"id":2262489,"name":"On or near Parking Area"},"longitude":"-2.742968"},"context":"","outcome_status":{"category":"Status update unavailable","date":"2025-12"},"persistent_id":"48e7e9018caff83fdad8ed7f09e1a0d695c3b497c99924bdb1eb09f1023b6293","id":131004124,"location_subtype":"","month":"2025-08"},{"category":"other-theft","location_type":"Force","location":{"latitude":"54.337662","street":{"id":2262387,"name":"On or near Aikrigg Avenue"},"longitude":"-2.747698"},"context":"","outcome_status":{"category":"Unable to prosecute suspect","date":"2025-12"},"persistent_id":"92f5ed10db3da6fb2e2b8ce14dfac5472a51ab8e157be49544253fc17ab64e89","id":131003961,"location_subtype":"","month":"2025-08"},{"category":"possession-of-weapons","location_type":"Force","location":{"latitude":"54.337163","street":{"id":2262326,"name":"On or near Charles Street"},"longitude":"-2.748350"},"context":"","outcome_status":{"category":"Status update unavailable","date":"2025-12"},"persistent_id":"564ab477fb0aae63795c37b11bdec808a876bb378d5a65ff96ac1568e9ddb38c","id":131005995,"location_subtype":"","month":"2025-08"},{"category":"public-order","location_type":"Force","location":{"latitude":"54.328431","street":{"id":2262423,"name":"On or near Branthwaite Brow"},"longitude":"-2.746408"},"context":"","outcome_status":{"category":"Status update unavailable","date":"2025-12"},"persistent_id":"680222ac6a9d85fc0f3ae7a56b611834ce735ca4c88044cb08856e30e51c2bd7","id":131005136,"location_subtype":"","month":"2025-08"},{"category":"public-order","location_type":"Force","location":{"latitude":"54.332406","street":{"id":2262401,"name":"On or near Police Station"},"longitude":"-2.747321"},"context":"","outcome_status":{"category":"Status update unavailable","date":"2025-12"},"persistent_id":"cc2aa1327a467e194e1d0a8f59f9371812722dc1d7e63a4d9272f5dff665159a","id":131004866,"location_subtype":"","month":"2025-08"},{"category":"public-order","location_type":"Force","location":{"latitude":"54.329064","street":{"id":2262334,"name":"On or near Shopping Area"},"longitude":"-2.750156"},"context":"","outcome_status":{"category":"Investigation complete; no suspect identified","date":"2025-08"},"persistent_id":"7df12e189665934024494a2633ce4ef7550bdb7771d97f79bdb0fe2178277632","id":131004910,"location_subtype":"","month":"2025-08"},{"category":"public-order","location_type":"Force","location":{"latitude":"54.333644","street":{"id":2262785,"name":"On or near Kentdale Road"},"longitude":"-2.730093"},"context":"","outcome_status":{"category":"Investigation complete; no suspect identified","date":"2025-08"},"persistent_id":"1a7e7b504a761eaa90e2fe09e13daae50dfb992b3ebb40383240b73f83124b5c","id":131005363,"location_subtype":"","month":"2025-08"},{"category":"public-order","location_type":"Force","location":{"latitude":"54.332406","street":{"id":2262401,"name":"On or near Police Station"},"longitude":"-2.747321"},"context":"","outcome_status":{"category":"Unable to prosecute suspect","date":"2026-01"},"persistent_id":"6da36df0ce42e9f6995d58daa584e4ef0b78bc4a0103c723637e5af5737f4cf6","id":131005486,"location_subtype":"","month":"2025-08"},{"category":"public-order","location_type":"Force","location":{"latitude":"54.312018","street":{"id":2262602,"name":"On or near Helme Drive"},"longitude":"-2.736458"},"context":"","outcome_status":{"category":"Local resolution","date":"2025-10"},"persistent_id":"ce05e542158c051b832e9cd20de0d82852dd892999156f8bbdf13244f2f533e2","id":131003940,"location_subtype":"","month":"2025-08"},{"category":"public-order","location_type":"Force","location":{"latitude":"54.316658","street":{"id":2262478,"name":"On or near Ford Terrace"},"longitude":"-2.743366"},"context":"","outcome_status":{"category":"Awaiting court outcome","date":"2025-08"},"persistent_id":"428ff04b06f2c466ebe763459655815be99f874d11ae125296d3b52d87a6674f","id":131005918,"location_subtype":"","month":"2025-08"},{"category":"public-order","location_type":"Force","location":{"latitude":"54.327229","street":{"id":2262439,"name":"On or near Parking Area"},"longitude":"-2.745987"},"context":"","outcome_status":{"category":"Unable to prosecute suspect","date":"2025-08"},"persistent_id":"2095b5fba52facc6a9d7d3724d08920942ecdacb1f2cfec491e544372d56920b","id":131004573,"location_subtype":"","month":"2025-08"},{"category":"public-order","location_type":"Force","location":{"latitude":"54.322431","street":{"id":2262343,"name":"On or near Buttery Well Road"},"longitude":"-2.748667"},"context":"","outcome_status":{"category":"Investigation complete; no suspect identified","date":"2025-08"},"persistent_id":"f14c10eef724bce8a061657917c293ac264aa6cc87ca486fad0215f09f122db7","id":131006164,"location_subtype":"","month":"2025-08"},{"category":"public-order","location_type":"Force","location":{"latitude":"54.320088","street":{"id":2262380,"name":"On or near Anchorite Road"},"longitude":"-2.748225"},"context":"","outcome_status":{"category":"Investigation complete; no suspect identified","date":"2025-08"},"persistent_id":"bc1c6d25fedbbb754e764f1491341160c42e303286a175464496ae3a98b73c04","id":131004673,"location_subtype":"","month":"2025-08"},{"category":"public-order","location_type":"Force","location":{"latitude":"54.330722","street":{"id":2262532,"name":"On or near Wildman Street"},"longitude":"-2.740652"},"context":"","outcome_status":{"category":"Unable to prosecute suspect","date":"2026-01"},"persistent_id":"526a952ddc4d4194bef1bdc9ea569542f53a52bdde9d73e46e8497d7db03bc5d","id":131006227,"location_subtype":"","month":"2025-08"},{"category":"public-order","location_type":"Force","location":{"latitude":"54.332406","street":{"id":2262401,"name":"On or near Police Station"},"longitude":"-2.747321"},"context":"","outcome_status":{"category":"Unable to prosecute suspect","date":"2026-01"},"persistent_id":"88e9e2facc09463cb68216925bdf3a02d99d02ff61ee6ec103b681b04ee9aa2b","id":131005492,"location_subtype":"","month":"2025-08"},{"category":"public-order","location_type":"Force","location":{"latitude":"54.323176","street":{"id":2262412,"name":"On or near Parking Area"},"longitude":"-2.745959"},"context":"","outcome_status":{"category":"Status update unavailable","date":"2025-12"},"persistent_id":"95e85d5df7eb9374f3e0b182aea791e0cc3e73880f77562a9c930da2f4346f66","id":131005716,"location_subtype":"","month":"2025-08"},{"category":"public-order","location_type":"Force","location":{"latitude":"54.329144","street":{"id":2262480,"name":"On or near Stramongate"},"longitude":"-2.742977"},"context":"","outcome_status":{"category":"Awaiting court outcome","date":"2025-08"},"persistent_id":"62dd4849a4b0262a9d810c95326e8dd2449c7add1fbb1c33df50e6b881798333","id":131006802,"location_subtype":"","month":"2025-08"},{"category":"public-order","location_type":"Force","location":{"latitude":"54.329144","street":{"id":2262480,"name":"On or near Stramongate"},"longitude":"-2.742977"},"context":"","outcome_status":{"category":"Unable to prosecute suspect","date":"2025-10"},"persistent_id":"2b7056c657ada8ee2e6922d674b1827a416a655982b2a3c0b66efd0ecab79290","id":131006843,"location_subtype":"","month":"2025-08"},{"category":"public-order","location_type":"Force","location":{"latitude":"54.326806","street":{"id":2262394,"name":"On or near A6"},"longitude":"-2.747563"},"context":"","outcome_status":{"category":"Unable to prosecute suspect","date":"2025-08"},"persistent_id":"7adbdbe888f3708024ede87e618bc6d6311efe367671d0331abf2838b16724d6","id":131005425,"location_subtype":"","month":"2025-08"},{"category":"public-order","location_type":"Force","location":{"latitude":"54.326790","street":{"id":2262408,"name":"On or near Lowther Street"},"longitude":"-2.747239"},"context":"","outcome_status":{"category":"Investigation complete; no suspect identified","date":"2025-08"},"persistent_id":"4d30cc07e98fd459dd850d8987dc3b2b59a2471ec70acb8aae7435a6f5f7b9e6","id":131004920,"location_subtype":"","month":"2025-08"},{"category":"public-order","location_type":"Force","location":{"latitude":"54.322431","street":{"id":2262343,"name":"On or near Buttery Well Road"},"longitude":"-2.748667"},"context":"","outcome_status":{"category":"Investigation complete; no suspect identified","date":"2025-08"},"persistent_id":"47b306f14994268e413977c15fbdcb9a0ecb154185e6ff27563797d010db5182","id":131006166,"location_subtype":"","month":"2025-08"},{"category":"public-order","location_type":"Force","location":{"latitude":"54.319206","street":{"id":2262263,"name":"On or near Vicars Fields"},"longitude":"-2.751299"},"context":"","outcome_status":{"category":"Unable to prosecute suspect","date":"2025-12"},"persistent_id":"7eda3bbad25e9afd5f064769171926a10ce62406f777fdab9c9864f2f108da42","id":131004041,"location_subtype":"","month":"2025-08"},{"category":"public-order","location_type":"Force","location":{"latitude":"54.326790","street":{"id":2262408,"name":"On or near Lowther Street"},"longitude":"-2.747239"},"context":"","outcome_status":{"category":"Unable to prosecute suspect","date":"2025-08"},"persistent_id":"41ff506edce55ed47bc7a282fdae150cf4b21245385e6248a23aef775125e7fc","id":131004207,"location_subtype":"","month":"2025-08"},{"category":"public-order","location_type":"Force","location":{"latitude":"54.330923","street":{"id":2262588,"name":"On or near Drysalters Yard"},"longitude":"-2.738672"},"context":"","outcome_status":{"category":"Unable to prosecute suspect","date":"2025-08"},"persistent_id":"346b30897b89ddc86d825b1b45a1d2e7af926b32b44a8dab468516c2633ca127","id":131004852,"location_subtype":"","month":"2025-08"},{"category":"robbery","location_type":"Force","location":{"latitude":"54.321912","street":{"id":2262427,"name":"On or near Kirkbarrow Lane"},"longitude":"-2.746874"},"context":"","outcome_status":{"category":"Unable to prosecute suspect","date":"2025-08"},"persistent_id":"f8f96b79b49e30c1adeae54eca38a8bdce209dd701dc95f82357b217b8131f6f","id":131005801,"location_subtype":"","month":"2025-08"},{"category":"shoplifting","location_type":"Force","location":{"latitude":"54.327229","street":{"id":2262439,"name":"On or near Parking Area"},"longitude":"-2.745987"},"context":"","outcome_status":{"category":"Further investigation is not in the public interest","date":"2025-10"},"persistent_id":"0bdee336fcfb5642601d4a3d4c6e4eac9fdfa7d5226dd1a38c95cc5fec01afc3","id":131006610,"location_subtype":"","month":"2025-08"},{"category":"shoplifting","location_type":"Force","location":{"latitude":"54.327546","street":{"id":2262366,"name":"On or near Old Shambles"},"longitude":"-2.748576"},"context":"","outcome_status":{"category":"Unable to prosecute suspect","date":"2025-09"},"persistent_id":"e8aeeed345e4f8649620c3c1eba0b340f04a0cf0931091b29194212d44ed946f","id":131004049,"location_subtype":"","month":"2025-08"},{"category":"shoplifting","location_type":"Force","location":{"latitude":"54.338627","street":{"id":2262587,"name":"On or near Finley Drive"},"longitude":"-2.739764"},"context":"","outcome_status":{"category":"Awaiting court outcome","date":"2026-01"},"persistent_id":"fa95237bd399e34278ad3cb5c8d8ee051fb8736b6c545056a6a7dea8399522cc","id":131006713,"location_subtype":"","month":"2025-08"},{"category":"shoplifting","location_type":"Force","location":{"latitude":"54.329540","street":{"id":2262405,"name":"On or near Stricklandgate"},"longitude":"-2.747289"},"context":"","outcome_status":{"category":"Unable to prosecute suspect","date":"2025-09"},"persistent_id":"c98170b8dad1602628addc7979c01226ce7da714c09a4cd740641110a8605d02","id":131004600,"location_subtype":"","month":"2025-08"},{"category":"shoplifting","location_type":"Force","location":{"latitude":"54.327546","street":{"id":2262366,"name":"On or near Old Shambles"},"longitude":"-2.748576"},"context":"","outcome_status":{"category":"Investigation complete; no suspect identified","date":"2025-10"},"persistent_id":"555b62b09df60f7de9ed779a947c2bc93aa1b36ddaaeafffdf3d387b55fc7913","id":131006683,"location_subtype":"","month":"2025-08"},{"category":"shoplifting","location_type":"Force","location":{"latitude":"54.327546","street":{"id":2262366,"name":"On or near Old Shambles"},"longitude":"-2.748576"},"context":"","outcome_status":{"category":"Unable to prosecute suspect","date":"2025-08"},"persistent_id":"e4e9f9d792f08cddf33f270668af2d1863c74b9afe5b3a267b92a5a0ee2a0f98","id":131004647,"location_subtype":"","month":"2025-08"},{"category":"shoplifting","location_type":"Force","location":{"latitude":"54.329739","street":{"id":2262434,"name":"On or near Bus/coach Station"},"longitude":"-2.745509"},"context":"","outcome_status":{"category":"Status update unavailable","date":"2025-12"},"persistent_id":"9b8dbd93daa29c27656dd5346a3d13e0470311cd2428c58ba832406db4dba6d2","id":131004884,"location_subtype":"","month":"2025-08"},{"category":"shoplifting","location_type":"Force","location":{"latitude":"54.329064","street":{"id":2262334,"name":"On or near Shopping Area"},"longitude":"-2.750156"},"context":"","outcome_status":{"category":"Investigation complete; no suspect identified","date":"2025-08"},"persistent_id":"63bb9b580621d1d3ae43bff4a652734bfead29e76389fc4fee367b0e4f8132e8","id":131004909,"location_subtype":"","month":"2025-08"},{"category":"shoplifting","location_type":"Force","location":{"latitude":"54.327546","street":{"id":2262366,"name":"On or near Old Shambles"},"longitude":"-2.748576"},"context":"","outcome_status":{"category":"Investigation complete; no suspect identified","date":"2025-10"},"persistent_id":"d6eaad4776b0594e9f84ae6285e3c7fe0b6f38178866d5acfbcdbd1850a0160d","id":131006682,"location_subtype":"","month":"2025-08"},{"category":"vehicle-crime","location_type":"Force","location":{"latitude":"54.331637","street":{"id":2262878,"name":"On or near Thirlmere Road"},"longitude":"-2.724675"},"context":"","outcome_status":{"category":"Investigation complete; no suspect identified","date":"2025-10"},"persistent_id":"40da478a06140b4c1bbe381b851a461f694e866966da9902526e56a6d5fa7eb4","id":131006318,"location_subtype":"","month":"2025-08"},{"category":"vehicle-crime","location_type":"Force","location":{"latitude":"54.315846","street":{"id":2262222,"name":"On or near Pembroke Court"},"longitude":"-2.752606"},"context":"","outcome_status":{"category":"Status update unavailable","date":"2025-12"},"persistent_id":"d44b1814ab201614a4b818af516129e541b70be35bafecb8e2722ebf60c92eed","id":131006336,"location_subtype":"","month":"2025-08"},{"category":"vehicle-crime","location_type":"Force","location":{"latitude":"54.337366","street":{"id":2262553,"name":"On or near Rosemede Avenue"},"longitude":"-2.740341"},"context":"","outcome_status":{"category":"Investigation complete; no suspect identified","date":"2025-10"},"persistent_id":"6b01221712339ac9ebacac56601f075044d5166fd7a94161c67048846ba4118c","id":131006197,"location_subtype":"","month":"2025-08"},{"category":"vehicle-crime","location_type":"Force","location":{"latitude":"54.315846","street":{"id":2262222,"name":"On or near Pembroke Court"},"longitude":"-2.752606"},"context":"","outcome_status":{"category":"Unable to prosecute suspect","date":"2025-09"},"persistent_id":"4a22fde69fae7b1644ea8084f634d8d1e3b906ff6d079429dc500ce5672437a0","id":131006744,"location_subtype":"","month":"2025-08"},{"category":"violent-crime","location_type":"Force","location":{"latitude":"54.320401","street":{"id":2262224,"name":"On or near Echo Barn Hill"},"longitude":"-2.752766"},"context":"","outcome_status":{"category":"Unable to prosecute suspect","date":"2025-09"},"persistent_id":"3c0d0588323373c4887cb366e88068e1586a84c637057e691d44c15f76291667","id":131006306,"location_subtype":"","month":"2025-08"},{"category":"violent-crime","location_type":"Force","location":{"latitude":"54.323167","street":{"id":2262320,"name":"On or near Gillinggate"},"longitude":"-2.750279"},"context":"","outcome_status":{"category":"Unable to prosecute suspect","date":"2025-09"},"persistent_id":"6205298a1ac20930115840860231e0209e7082322367d08cddd2bef8b12dcc30","id":131007034,"location_subtype":"","month":"2025-08"},{"category":"violent-crime","location_type":"Force","location":{"latitude":"54.327546","street":{"id":2262366,"name":"On or near Old Shambles"},"longitude":"-2.748576"},"context":"","outcome_status":{"category":"Unable to prosecute suspect","date":"2025-09"},"persistent_id":"be168c7e137ccd3f076f4ac534d9f4a57b8e14784101cb5a85d880e3dc49d2f4","id":131006965,"location_subtype":"","month":"2025-08"},{"category":"violent-crime","location_type":"Force","location":{"latitude":"54.338816","street":{"id":2262322,"name":"On or near Burneside Road"},"longitude":"-2.748565"},"context":"","outcome_status":{"category":"Investigation complete; no suspect identified","date":"2025-08"},"persistent_id":"680de3cf3e010dfacfcb71fcd534a54e73137128cc5795121f835d89cb089ef0","id":131003895,"location_subtype":"","month":"2025-08"},{"category":"violent-crime","location_type":"Force","location":{"latitude":"54.333898","street":{"id":2262728,"name":"On or near Broad Ing Crescent"},"longitude":"-2.732743"},"context":"","outcome_status":{"category":"Status update unavailable","date":"2025-12"},"persistent_id":"4348090cd09a2f581c2e3d0500b140c67f4c33a6dcbe29f740853bc560b1d164","id":131004052,"location_subtype":"","month":"2025-08"},{"category":"violent-crime","location_type":"Force","location":{"latitude":"54.330923","street":{"id":2262588,"name":"On or near Drysalters Yard"},"longitude":"-2.738672"},"context":"","outcome_status":{"category":"Unable to prosecute suspect","date":"2025-09"},"persistent_id":"89b5aff75d066b6184175a2f02ae26fdd11597a4e01d66f7a6a0e62fdfd16ac4","id":131004302,"location_subtype":"","month":"2025-08"},{"category":"violent-crime","location_type":"Force","location":{"latitude":"54.329093","street":{"id":2262705,"name":"On or near Castle Road"},"longitude":"-2.733765"},"context":"","outcome_status":{"category":"Unable to prosecute suspect","date":"2025-08"},"persistent_id":"9d781ea21499a7061bbb2a8957ce98a2a7faf12a6ab2ab6d7dbbbbac6b8c7026","id":131004369,"location_subtype":"","month":"2025-08"},{"category":"violent-crime","location_type":"Force","location":{"latitude":"54.326235","street":{"id":2262360,"name":"On or near Collin Croft"},"longitude":"-2.748306"},"context":"","outcome_status":{"category":"Unable to prosecute suspect","date":"2026-01"},"persistent_id":"976da06b163f4f46b8118c6fad929b4393e76cf729c07d4e453be8998ea05231","id":131004446,"location_subtype":"","month":"2025-08"},{"category":"violent-crime","location_type":"Force","location":{"latitude":"54.338693","street":{"id":2262306,"name":"On or near Sparrowmire Lane"},"longitude":"-2.750993"},"context":"","outcome_status":{"category":"Status update unavailable","date":"2025-12"},"persistent_id":"9797732d48fa1ba728647b1855d46073133252d4a6f2a5d45d0bc5eacb38e63f","id":131004529,"location_subtype":"","month":"2025-08"},{"category":"violent-crime","location_type":"Force","location":{"latitude":"54.322415","street":{"id":2262809,"name":"On or near Castle Rise"},"longitude":"-2.729356"},"context":"","outcome_status":{"category":"Unable to prosecute suspect","date":"2025-08"},"persistent_id":"303aa34873196182b4016536ee4f3d58d33a04232d81c31a89e8f9a952c4d3cc","id":131004560,"location_subtype":"","month":"2025-08"},{"category":"violent-crime","location_type":"Force","location":{"latitude":"54.331600","street":{"id":2262455,"name":"On or near Beezon Fields"},"longitude":"-2.744036"},"context":"","outcome_status":{"category":"Unable to prosecute suspect","date":"2025-10"},"persistent_id":"a23fe599e971d47984fd0bcaea2192663a00f5d4116168aa51b18594d7037675","id":131004923,"location_subtype":"","month":"2025-08"},{"category":"violent-crime","location_type":"Force","location":{"latitude":"54.327605","street":{"id":2262457,"name":"On or near Kent Street"},"longitude":"-2.744763"},"context":"","outcome_status":{"category":"Unable to prosecute suspect","date":"2025-08"},"persistent_id":"1b2730a725390c8c2267a5389eeabed633a6923909f407fe4ab9da8c111878a9","id":131005524,"location_subtype":"","month":"2025-08"},{"category":"violent-crime","location_type":"Force","location":{"latitude":"54.332137","street":{"id":2262589,"name":"On or near Stockbeck"},"longitude":"-2.738509"},"context":"","outcome_status":{"category":"Unable to prosecute suspect","date":"2025-10"},"persistent_id":"5d87691dcc556a9730b32bfebb000d41d40642b611a8b2d1a5b4bb32ec45f859","id":131005532,"location_subtype":"","month":"2025-08"},{"category":"violent-crime","location_type":"Force","location":{"latitude":"54.326902","street":{"id":2262341,"name":"On or near Parking Area"},"longitude":"-2.749440"},"context":"","outcome_status":{"category":"Unable to prosecute suspect","date":"2025-08"},"persistent_id":"73f206f1a3e7d7684ff5c7941ac0461644f2c4a31419f897094ec9ec0ade2b96","id":131005538,"location_subtype":"","month":"2025-08"},{"category":"violent-crime","location_type":"Force","location":{"latitude":"54.338693","street":{"id":2262306,"name":"On or near Sparrowmire Lane"},"longitude":"-2.750993"},"context":"","outcome_status":{"category":"Status update unavailable","date":"2025-12"},"persistent_id":"3962bbbd177f6fde5aeaced9d7dd3db7632eb371e64646c75a93c3c5339d6b84","id":131005570,"location_subtype":"","month":"2025-08"},{"category":"violent-crime","location_type":"Force","location":{"latitude":"54.331600","street":{"id":2262455,"name":"On or near Beezon Fields"},"longitude":"-2.744036"},"context":"","outcome_status":{"category":"Unable to prosecute suspect","date":"2025-12"},"persistent_id":"ba67d92707bd4096e180b13cdfa8f4a0c0a1179f23d9a944c034fef6b8c820d9","id":131005711,"location_subtype":"","month":"2025-08"},{"category":"violent-crime","location_type":"Force","location":{"latitude":"54.331881","street":{"id":2262569,"name":"On or near Longpool"},"longitude":"-2.739289"},"context":"","outcome_status":{"category":"Unable to prosecute suspect","date":"2025-08"},"persistent_id":"497c2ff16a4bcad40f4ff938f7dc94e68b632d7ed8dc4e3b13b5a9cb53f8caa9","id":131005745,"location_subtype":"","month":"2025-08"},{"category":"violent-crime","location_type":"Force","location":{"latitude":"54.331068","street":{"id":2262875,"name":"On or near Coniston Drive"},"longitude":"-2.726665"},"context":"","outcome_status":{"category":"Status update unavailable","date":"2025-12"},"persistent_id":"1da050f2523ccc3e1e0a185b0ae1979c48ecc21e94d78330336daae776ce60b4","id":131006161,"location_subtype":"","month":"2025-08"},{"category":"violent-crime","location_type":"Force","location":{"latitude":"54.314015","street":{"id":2262711,"name":"On or near Tarn Close"},"longitude":"-2.733189"},"context":"","outcome_status":{"category":"Unable to prosecute suspect","date":"2025-09"},"persistent_id":"73f0ffe7414bbf2ca9c0b1998f607ccc21704d421366569e0afe1a2ece73f163","id":131006277,"location_subtype":"","month":"2025-08"},{"category":"violent-crime","location_type":"Force","location":{"latitude":"54.312018","street":{"id":2262602,"name":"On or near Helme Drive"},"longitude":"-2.736458"},"context":"","outcome_status":{"category":"Local resolution","date":"2025-08"},"persistent_id":"8c4835af9c9a68c7eaa19ea5dfb4d1e51f9ffd650af1167f7df284efca82d82a","id":131003826,"location_subtype":"","month":"2025-08"},{"category":"violent-crime","location_type":"Force","location":{"latitude":"54.319206","street":{"id":2262263,"name":"On or near Vicars Fields"},"longitude":"-2.751299"},"context":"","outcome_status":{"category":"Local resolution","date":"2025-10"},"persistent_id":"6fc42c6a6562c229c051dfeb22f7a73a8411b115a694d886f91e3a33ef9357b8","id":131004036,"location_subtype":"","month":"2025-08"},{"category":"violent-crime","location_type":"Force","location":{"latitude":"54.338693","street":{"id":2262306,"name":"On or near Sparrowmire Lane"},"longitude":"-2.750993"},"context":"","outcome_status":{"category":"Status update unavailable","date":"2025-12"},"persistent_id":"10d072980323b3540f24a6f84a0015cde28fa437e2523a3a2f695aeecd915722","id":131004530,"location_subtype":"","month":"2025-08"},{"category":"violent-crime","location_type":"Force","location":{"latitude":"54.330515","street":{"id":2262331,"name":"On or near Nobles Place"},"longitude":"-2.749491"},"context":"","outcome_status":{"category":"Unable to prosecute suspect","date":"2026-01"},"persistent_id":"1963e7f70d2ebf970b385ae1be097cae8ffeafbc38b8dd1de95bc5cbd6c4883a","id":131005287,"location_subtype":"","month":"2025-08"},{"category":"violent-crime","location_type":"Force","location":{"latitude":"54.332140","street":{"id":2262287,"name":"On or near Town View"},"longitude":"-2.751135"},"context":"","outcome_status":{"category":"Status update unavailable","date":"2025-12"},"persistent_id":"dcc07f8c4da91574cd5cec109132d8d33daf73f06ce4b21c64e5056cf12c7357","id":131005751,"location_subtype":"","month":"2025-08"},{"category":"violent-crime","location_type":"Force","location":{"latitude":"54.326902","street":{"id":2262341,"name":"On or near Parking Area"},"longitude":"-2.749440"},"context":"","outcome_status":{"category":"Unable to prosecute suspect","date":"2025-10"},"persistent_id":"3c9565e7189aabcc206f037e21a872b8a01a0b51e75cc2dc57c19c886ce6c98a","id":131005835,"location_subtype":"","month":"2025-08"},{"category":"violent-crime","location_type":"Force","location":{"latitude":"54.321931","street":{"id":2262447,"name":"On or near Kirkland"},"longitude":"-2.745214"},"context":"","outcome_status":{"category":"Unable to prosecute suspect","date":"2025-10"},"persistent_id":"dc4257503116c3587b4a33ea526170c948aa0258b263b032474ea2a7a5f7627e","id":131006704,"location_subtype":"","month":"2025-08"},{"category":"violent-crime","location_type":"Force","location":{"latitude":"54.324286","street":{"id":2262415,"name":"On or near Dowker's Lane"},"longitude":"-2.746610"},"context":"","outcome_status":{"category":"Status update unavailable","date":"2025-12"},"persistent_id":"7f5f85f165a106d07def120102f0a4a60b175fb2e933044ca1bad42462d380e6","id":131003840,"location_subtype":"","month":"2025-08"},{"category":"violent-crime","location_type":"Force","location":{"latitude":"54.334401","street":{"id":2262767,"name":"On or near Garburn Road"},"longitude":"-2.729861"},"context":"","outcome_status":{"category":"Further investigation is not in the public interest","date":"2025-08"},"persistent_id":"4adc88c3a8d808b3cc1e3cbd91a463dcf5db215cfd07708b8ec1603005335636","id":131004048,"location_subtype":"","month":"2025-08"},{"category":"violent-crime","location_type":"Force","location":{"latitude":"54.327546","street":{"id":2262366,"name":"On or near Old Shambles"},"longitude":"-2.748576"},"context":"","outcome_status":{"category":"Unable to prosecute suspect","date":"2025-08"},"persistent_id":"771e91a5ae14324af91033a93503eb5b9aba88febb6d5c36d1bfe09b3c701c84","id":131004130,"location_subtype":"","month":"2025-08"},{"category":"violent-crime","location_type":"Force","location":{"latitude":"54.330923","street":{"id":2262588,"name":"On or near Drysalters Yard"},"longitude":"-2.738672"},"context":"","outcome_status":{"category":"Unable to prosecute suspect","date":"2025-09"},"persistent_id":"774d338233244070d44ca79f45406c3b0714b2fa1c79dd61ee29f2946adb0c57","id":131004306,"location_subtype":"","month":"2025-08"},{"category":"violent-crime","location_type":"Force","location":{"latitude":"54.327605","street":{"id":2262457,"name":"On or near Kent Street"},"longitude":"-2.744763"},"context":"","outcome_status":{"category":"Unable to prosecute suspect","date":"2025-09"},"persistent_id":"ef9fe230ade7bd050095d476e4afb57397347a71d288c3b79acba82bc733049b","id":131004312,"location_subtype":"","month":"2025-08"},{"category":"violent-crime","location_type":"Force","location":{"latitude":"54.329093","street":{"id":2262705,"name":"On or near Castle Road"},"longitude":"-2.733765"},"context":"","outcome_status":{"category":"Unable to prosecute suspect","date":"2025-08"},"persistent_id":"e40720f8e28b4b99c48c870e5ccd966bd856c67bfb1d6926abec0f7f82401ec5","id":131004362,"location_subtype":"","month":"2025-08"},{"category":"violent-crime","location_type":"Force","location":{"latitude":"54.321048","street":{"id":2262266,"name":"On or near Well Ings"},"longitude":"-2.751379"},"context":"","outcome_status":{"category":"Status update unavailable","date":"2025-12"},"persistent_id":"718220c784c6692a2610fcf997d4318338883f7eed064dded8644eaefc0e2abc","id":131004400,"location_subtype":"","month":"2025-08"},{"category":"violent-crime","location_type":"Force","location":{"latitude":"54.332140","street":{"id":2262287,"name":"On or near Town View"},"longitude":"-2.751135"},"context":"","outcome_status":{"category":"Status update unavailable","date":"2025-12"},"persistent_id":"5e485cdf4e1aba95715919446a34c23568eace12baf4d9f731c1fe8f2b15bc62","id":131004626,"location_subtype":"","month":"2025-08"},{"category":"violent-crime","location_type":"Force","location":{"latitude":"54.335546","street":{"id":2262182,"name":"On or near Underley Road"},"longitude":"-2.755457"},"context":"","outcome_status":{"category":"Local resolution","date":"2025-08"},"persistent_id":"b7d545caaed3a26561fbaa1e39e6af5dcec6f7777b7e221706c576846ce54ae2","id":131004682,"location_subtype":"","month":"2025-08"},{"category":"violent-crime","location_type":"Force","location":{"latitude":"54.333360","street":{"id":2262725,"name":"On or near Crag View"},"longitude":"-2.732457"},"context":"","outcome_status":{"category":"Unable to prosecute suspect","date":"2025-10"},"persistent_id":"73a3f4867e4c221e1f7829b3616854abc788671578d9200841c94c1229a76f0c","id":131004733,"location_subtype":"","month":"2025-08"},{"category":"violent-crime","location_type":"Force","location":{"latitude":"54.332140","street":{"id":2262287,"name":"On or near Town View"},"longitude":"-2.751135"},"context":"","outcome_status":{"category":"Unable to prosecute suspect","date":"2025-10"},"persistent_id":"15ba439747aee023c20d8c23ccb0976a91fc9e4872ca211d9611871e67baea0c","id":131004816,"location_subtype":"","month":"2025-08"},{"category":"violent-crime","location_type":"Force","location":{"latitude":"54.326900","street":{"id":2262459,"name":"On or near Bridge Street"},"longitude":"-2.743997"},"context":"","outcome_status":{"category":"Status update unavailable","date":"2025-12"},"persistent_id":"877ad780d23bfca87529b173280e01f2930035214a611bebc6fda186e849c01c","id":131004899,"location_subtype":"","month":"2025-08"},{"category":"violent-crime","location_type":"Force","location":{"latitude":"54.313207","street":{"id":2262596,"name":"On or near Helme Close"},"longitude":"-2.737509"},"context":"","outcome_status":{"category":"Unable to prosecute suspect","date":"2025-08"},"persistent_id":"5bfb71318c1925c41f49dab94b76f604f8192f3afd6dd0459cceb2f58ae67d03","id":131004931,"location_subtype":"","month":"2025-08"},{"category":"violent-crime","location_type":"Force","location":{"latitude":"54.325115","street":{"id":2262422,"name":"On or near Kent Place"},"longitude":"-2.746287"},"context":"","outcome_status":{"category":"Status update unavailable","date":"2025-12"},"persistent_id":"5f19a4f59aaa49fcfb14c3b61aa30f421f0c5847cc6d4234190bc86cddca116a","id":131005103,"location_subtype":"","month":"2025-08"},{"category":"violent-crime","location_type":"Force","location":{"latitude":"54.313968","street":{"id":2262552,"name":"On or near Burland Grove"},"longitude":"-2.739429"},"context":"","outcome_status":{"category":"Unable to prosecute suspect","date":"2025-10"},"persistent_id":"12822cd2da42836776a8dea7817b8311b5eedeb716ec1911b68c375b1f239bf4","id":131005237,"location_subtype":"","month":"2025-08"},{"category":"violent-crime","location_type":"Force","location":{"latitude":"54.325036","street":{"id":2262403,"name":"On or near Highgate"},"longitude":"-2.747500"},"context":"","outcome_status":{"category":"Unable to prosecute suspect","date":"2025-09"},"persistent_id":"aac4c5acfa5fa15a070e04fc4905c95a92d430e5149b42a46da5db4296a08e82","id":131005357,"location_subtype":"","month":"2025-08"},{"category":"violent-crime","location_type":"Force","location":{"latitude":"54.321931","street":{"id":2262447,"name":"On or near Kirkland"},"longitude":"-2.745214"},"context":"","outcome_status":{"category":"Unable to prosecute suspect","date":"2025-10"},"persistent_id":"cab5a3cd5dab3dd83d8b2ccd608e73c0d997997916d11fdb0911fd0724762552","id":131005377,"location_subtype":"","month":"2025-08"},{"category":"violent-crime","location_type":"Force","location":{"latitude":"54.321931","street":{"id":2262447,"name":"On or near Kirkland"},"longitude":"-2.745214"},"context":"","outcome_status":{"category":"Unable to prosecute suspect","date":"2025-10"},"persistent_id":"09c5fa4589fa89870d78a6008f0d9ab84b73ebdf8409ab4d9a01c332db63d212","id":131005383,"location_subtype":"","month":"2025-08"},{"category":"violent-crime","location_type":"Force","location":{"latitude":"54.327823","street":{"id":2262489,"name":"On or near Parking Area"},"longitude":"-2.742968"},"context":"","outcome_status":{"category":"Unable to prosecute suspect","date":"2025-08"},"persistent_id":"7a7647e966ba11ede523ffe72759b49b4d94daabc0d2886adbb999af3efc3ae1","id":131005413,"location_subtype":"","month":"2025-08"},{"category":"violent-crime","location_type":"Force","location":{"latitude":"54.327605","street":{"id":2262457,"name":"On or near Kent Street"},"longitude":"-2.744763"},"context":"","outcome_status":{"category":"Unable to prosecute suspect","date":"2025-10"},"persistent_id":"e922bbbe59bab359d4f20cd965517c6ff0a7fede3d9238f4f3e470b6d1950ae8","id":131005528,"location_subtype":"","month":"2025-08"},{"category":"violent-crime","location_type":"Force","location":{"latitude":"54.326902","street":{"id":2262341,"name":"On or near Parking Area"},"longitude":"-2.749440"},"context":"","outcome_status":{"category":"Unable to prosecute suspect","date":"2025-08"},"persistent_id":"e6c735d5e55be3c873fee870d4b0a336c01badb8c9b1c854c954b242f81f1c10","id":131005535,"location_subtype":"","month":"2025-08"},{"category":"violent-crime","location_type":"Force","location":{"latitude":"54.327605","street":{"id":2262457,"name":"On or near Kent Street"},"longitude":"-2.744763"},"context":"","outcome_status":{"category":"Investigation complete; no suspect identified","date":"2025-10"},"persistent_id":"10d51e28b0f30c55dc3c9599fc69e123c351febb5d4b09fa4123a6f816c6cf56","id":131005540,"location_subtype":"","month":"2025-08"},{"category":"violent-crime","location_type":"Force","location":{"latitude":"54.333360","street":{"id":2262725,"name":"On or near Crag View"},"longitude":"-2.732457"},"context":"","outcome_status":{"category":"Unable to prosecute suspect","date":"2025-11"},"persistent_id":"6f84e9818effaeba6a4ac915f69c52219b047b8dcb6c49cd7039f2bbc89a8c16","id":131005903,"location_subtype":"","month":"2025-08"},{"category":"violent-crime","location_type":"Force","location":{"latitude":"54.336786","street":{"id":2262533,"name":"On or near Mint Dale"},"longitude":"-2.741115"},"context":"","outcome_status":{"category":"Status update unavailable","date":"2025-12"},"persistent_id":"b623defd62bb44fa57ea0ff3696369377cdecc9ed89771c73b13ee50838d635b","id":131006015,"location_subtype":"","month":"2025-08"},{"category":"violent-crime","location_type":"Force","location":{"latitude":"54.333894","street":{"id":2262342,"name":"On or near Rydal Mount"},"longitude":"-2.749521"},"context":"","outcome_status":{"category":"Status update unavailable","date":"2025-12"},"persistent_id":"5606809abe2a5ebad800fbc84e48ff9f8352f73c718f46f9ff692d9aa37f0481","id":131006035,"location_subtype":"","month":"2025-08"},{"category":"violent-crime","location_type":"Force","location":{"latitude":"54.324215","street":{"id":2262737,"name":"On or near Castle Drive"},"longitude":"-2.731817"},"context":"","outcome_status":{"category":"Unable to prosecute suspect","date":"2025-08"},"persistent_id":"6e489321af155fe1de827eb9fd00c82024c76e0f0de61fa6ddebb38dc2a7b024","id":131006198,"location_subtype":"","month":"2025-08"},{"category":"violent-crime","location_type":"Force","location":{"latitude":"54.333455","street":{"id":2262645,"name":"On or near Drovers Drive"},"longitude":"-2.736180"},"context":"","outcome_status":{"category":"Unable to prosecute suspect","date":"2025-09"},"persistent_id":"b4ab2f4301cf9715abfd5c60e85b2a0d492facdcb2a0ddba31e830e281753b82","id":131006311,"location_subtype":"","month":"2025-08"},{"category":"violent-crime","location_type":"Force","location":{"latitude":"54.326790","street":{"id":2262408,"name":"On or near Lowther Street"},"longitude":"-2.747239"},"context":"","outcome_status":{"category":"Unable to prosecute suspect","date":"2025-09"},"persistent_id":"d6e83ef7c12b90397529ff3867332ec4caf6a324fbb61f0f972671ecf67e1d63","id":131007035,"location_subtype":"","month":"2025-08"},{"category":"violent-crime","location_type":"Force","location":{"latitude":"54.332406","street":{"id":2262401,"name":"On or near Police Station"},"longitude":"-2.747321"},"context":"","outcome_status":{"category":"Awaiting court outcome","date":"2025-08"},"persistent_id":"afb2a5c3c4586e7e8bca6e37444ab88a840404baf34c9bec5a9d2ff040ef71e2","id":131006421,"location_subtype":"","month":"2025-08"},{"category":"violent-crime","location_type":"Force","location":{"latitude":"54.321931","street":{"id":2262447,"name":"On or near Kirkland"},"longitude":"-2.745214"},"context":"","outcome_status":{"category":"Unable to prosecute suspect","date":"2025-09"},"persistent_id":"54ac260da0743b26de9071bf8d1af7526281697e36e35bc9e68564c8e6eb5ee2","id":131006541,"location_subtype":"","month":"2025-08"},{"category":"violent-crime","location_type":"Force","location":{"latitude":"54.332884","street":{"id":2262317,"name":"On or near Cross Street"},"longitude":"-2.749995"},"context":"","outcome_status":{"category":"Unable to prosecute suspect","date":"2025-12"},"persistent_id":"28e818614938989b00360a7d5e42c34844419d97d24922ec1ed52ed95c8672da","id":131006560,"location_subtype":"","month":"2025-08"},{"category":"violent-crime","location_type":"Force","location":{"latitude":"54.333838","street":{"id":2262611,"name":"On or near Vine Road"},"longitude":"-2.738140"},"context":"","outcome_status":{"category":"Unable to prosecute suspect","date":"2025-09"},"persistent_id":"89725e9d392c3fcf5e908615ec75cd50c500a79ae4b17ef4c5a67160c7ef0a74","id":131006718,"location_subtype":"","month":"2025-08"},{"category":"violent-crime","location_type":"Force","location":{"latitude":"54.331954","street":{"id":2262359,"name":"On or near Busher Walk"},"longitude":"-2.747779"},"context":"","outcome_status":{"category":"Status update unavailable","date":"2025-12"},"persistent_id":"dfdfd8ff475e7c547ed2702eca263816cba1a02d238802685170b4c0576da3fb","id":131006813,"location_subtype":"","month":"2025-08"},{"category":"violent-crime","location_type":"Force","location":{"latitude":"54.322979","street":{"id":2262429,"name":"On or near Parking Area"},"longitude":"-2.745879"},"context":"","outcome_status":{"category":"Unable to prosecute suspect","date":"2025-08"},"persistent_id":"435c31a0381190b2921d28c2b6fa07db9e2580984bcd017f9038b655a5761100","id":131003854,"location_subtype":"","month":"2025-08"},{"category":"violent-crime","location_type":"Force","location":{"latitude":"54.332140","street":{"id":2262287,"name":"On or near Town View"},"longitude":"-2.751135"},"context":"","outcome_status":{"category":"Unable to prosecute suspect","date":"2025-08"},"persistent_id":"b6bb01280953d1feff4e5ec8999b64ba0169c32aaeeba838df016f69d50e3db6","id":131004834,"location_subtype":"","month":"2025-08"},{"category":"violent-crime","location_type":"Force","location":{"latitude":"54.321834","street":{"id":2262253,"name":"On or near Greengate Lane"},"longitude":"-2.752269"},"context":"","outcome_status":{"category":"Unable to prosecute suspect","date":"2025-08"},"persistent_id":"f540f647e3da77a2a540d255a0b459073864286b61743ece8eb42ae16d721e43","id":131004890,"location_subtype":"","month":"2025-08"},{"category":"violent-crime","location_type":"Force","location":{"latitude":"54.337366","street":{"id":2262553,"name":"On or near Rosemede Avenue"},"longitude":"-2.740341"},"context":"","outcome_status":{"category":"Formal action is not in the public interest","date":"2025-08"},"persistent_id":"7a0fe41d6d7d0e66488679363bdb07cafbcd69bb3ab88daa5668c7ba60c4dff8","id":131005040,"location_subtype":"","month":"2025-08"},{"category":"violent-crime","location_type":"Force","location":{"latitude":"54.329739","street":{"id":2262434,"name":"On or near Bus/coach Station"},"longitude":"-2.745509"},"context":"","outcome_status":{"category":"Action to be taken by another organisation","date":"2025-09"},"persistent_id":"f2b8e51d652996b2f621321eb261936e5d4c997feaa6bfbd563fd44d352947bb","id":131005802,"location_subtype":"","month":"2025-08"},{"category":"violent-crime","location_type":"Force","location":{"latitude":"54.321931","street":{"id":2262447,"name":"On or near Kirkland"},"longitude":"-2.745214"},"context":"","outcome_status":{"category":"Unable to prosecute suspect","date":"2025-09"},"persistent_id":"5a43d9508e11254d5950591c2b449b2029ed36b87fc65dab164d0e32656ecd38","id":131006540,"location_subtype":"","month":"2025-08"},{"category":"violent-crime","location_type":"Force","location":{"latitude":"54.315968","street":{"id":2262656,"name":"On or near Hayfell Avenue"},"longitude":"-2.735652"},"context":"","outcome_status":{"category":"Unable to prosecute suspect","date":"2025-09"},"persistent_id":"26e51558fca9e85c11643d0623f1e45c9769ad8f5344d4789ce746b272a688a3","id":131006555,"location_subtype":"","month":"2025-08"},{"category":"violent-crime","location_type":"Force","location":{"latitude":"54.327546","street":{"id":2262366,"name":"On or near Old Shambles"},"longitude":"-2.748576"},"context":"","outcome_status":{"category":"Further investigation is not in the public interest","date":"2025-09"},"persistent_id":"9c825dc3bb0ca9770ef136fecbb1c8db6b6fbef58b6e874774d3d2c94bfd23eb","id":131007053,"location_subtype":"","month":"2025-08"},{"category":"violent-crime","location_type":"Force","location":{"latitude":"54.322979","street":{"id":2262429,"name":"On or near Parking Area"},"longitude":"-2.745879"},"context":"","outcome_status":{"category":"Unable to prosecute suspect","date":"2025-09"},"persistent_id":"a3dedf8cbec4bc908fe5eb9cc9d63c94061a010bcfa876e0360a3bda558490a5","id":131004768,"location_subtype":"","month":"2025-08"},{"category":"other-crime","location_type":"Force","location":{"latitude":"54.333898","street":{"id":2262728,"name":"On or near Broad Ing Crescent"},"longitude":"-2.732743"},"context":"","outcome_status":{"category":"Awaiting court outcome","date":"2025-09"},"persistent_id":"692153aa7c14a1620a41f6d1976ecf2290b13c990fe7d0afa9750cc633642927","id":131003883,"location_subtype":"","month":"2025-08"},{"category":"other-crime","location_type":"Force","location":{"latitude":"54.332140","street":{"id":2262287,"name":"On or near Town View"},"longitude":"-2.751135"},"context":"","outcome_status":{"category":"Awaiting court outcome","date":"2025-10"},"persistent_id":"bad827dfc6e22439062dd2535c4bcf9cffccdc4b8524d09b8dec49e3c85aa381","id":131004813,"location_subtype":"","month":"2025-08"},{"category":"other-crime","location_type":"Force","location":{"latitude":"54.315846","street":{"id":2262222,"name":"On or near Pembroke Court"},"longitude":"-2.752606"},"context":"","outcome_status":{"category":"Investigation complete; no suspect identified","date":"2025-08"},"persistent_id":"8a0ecff4965a375be874052d37cfe4daebe1fe73927f09b69d5830ee70e24605","id":131004020,"location_subtype":"","month":"2025-08"},{"category":"other-crime","location_type":"Force","location":{"latitude":"54.312620","street":{"id":2262712,"name":"On or near Murley Moss Lane"},"longitude":"-2.733533"},"context":"","outcome_status":{"category":"Awaiting court outcome","date":"2025-09"},"persistent_id":"b1d9e9d1588c6002b4b29eb2f941f6f023b34aa229d916cb2ea2de70216840e1","id":131003889,"location_subtype":"","month":"2025-08"}]