[{"category":"anti-social-behaviour","location_type":"Force","location":{"latitude":"53.411526","street":{"id":1505678,"name":"On or near Bach Tyddyn"},"longitude":"-4.455780"},"context":"","outcome_status":null,"persistent_id":"","id":127360538,"location_subtype":"","month":"2025-04"},{"category":"anti-social-behaviour","location_type":"Force","location":{"latitude":"53.413527","street":{"id":1505706,"name":"On or near Parking Area"},"longitude":"-4.449004"},"context":"","outcome_status":null,"persistent_id":"","id":127361085,"location_subtype":"","month":"2025-04"},{"category":"public-order","location_type":"Force","location":{"latitude":"53.411903","street":{"id":1505681,"name":"On or near Maes Cynfor"},"longitude":"-4.454944"},"context":"","outcome_status":{"category":"Unable to prosecute suspect","date":"2025-06"},"persistent_id":"29e866f5125418757c038a339e6b243a0c3459b298016ff6f157d5d46234b719","id":127362401,"location_subtype":"","month":"2025-04"},{"category":"violent-crime","location_type":"Force","location":{"latitude":"53.411440","street":{"id":1505686,"name":"On or near Victoria Road"},"longitude":"-4.453398"},"context":"","outcome_status":{"category":"Status update unavailable","date":"2025-08"},"persistent_id":"aabdc4f9bf43b70b6ef0bcb63ada31325ec3f5fc458777b08c9c0c320a38fccc","id":127362682,"location_subtype":"","month":"2025-04"},{"category":"violent-crime","location_type":"Force","location":{"latitude":"53.411095","street":{"id":1505696,"name":"On or near High Street"},"longitude":"-4.452731"},"context":"","outcome_status":{"category":"Unable to prosecute suspect","date":"2025-08"},"persistent_id":"83f97bc93db1358709d3f16f115e8bf3d8d4ed962fe5e09f9600bb34a3c8ccc7","id":127364676,"location_subtype":"","month":"2025-04"}]